NULL_PROCESSEUR_V2/FIFO/fifo_72b.vhdl
LIBRARY ieee;
use ieee.std_logic_1164.all;

ENTITY fifo_72b IS
	PORT(
		din		: in std_logic_vector(71 downto 0);
		dout		: out std_logic_vector(71 downto 0);

		-- commands
		push		: in std_logic;
		pop		: in std_logic;

		-- flags
		full		: out std_logic;
		empty		: out std_logic;

		reset_n	: in std_logic;
		ck			: in std_logic;
		vdd		: in bit;
		vss		: in bit
	);
END fifo_72b;

architecture dataflow of fifo_72b is

signal fifo_d	: std_logic_vector(71 downto 0);
signal fifo_v	: std_logic;

begin

	process(ck)
		begin
		if rising_edge(ck) then
			-- Valid bit
			if reset_n = '0' then
				fifo_v <= '0';
			else
				if fifo_v = '0' then
					if push = '1' then
						fifo_v <= '1';
					else
						fifo_v <= '0';
					end if;
				else
					if pop = '1' then
						if push = '1' then
							fifo_v <= '1';
						else
							fifo_v <= '0';
						end if;
					else
						fifo_v <= '1';
					end if;
				end if;
			end if;

			-- data
			if fifo_v = '0' then
				if push = '1' then
					fifo_d <= din;
				end if;
			elsif push='1' and pop='1' then
					fifo_d <= din;
			end if;
		end if;
	end process;

	full <= '1' when fifo_v = '1' and pop = '0' else '0';
	empty <= not fifo_v;
	dout <= fifo_d;

end dataflow;

EXEC/src/shifter.vhdl
LIBRARY IEEE;
use IEEE.std_logic_1164.all;
use IEEE.numeric_std.all;

entity Shifter is
port( shift_lsl : in Std_Logic;
      shift_lsr : in Std_Logic;
      shift_asr : in Std_Logic;
      shift_ror : in Std_Logic;
      shift_rrx : in Std_Logic;
      shift_val : in Std_Logic_Vector(4 downto 0);
      din : in Std_Logic_Vector(31 downto 0);
      cin : in Std_Logic;
      dout : out Std_Logic_Vector(31 downto 0);
      cout : out Std_Logic;
      -- global interface
      vdd : in bit;
      vss : in bit);
end Shifter;

architecture behavior of Shifter is
--signal flag : std_logic_vector(4 downto 0) := shift_lsl & shift_lsr & shift_asr & shift_ror & shift_rrx;
--signal zero, msb_asr : std_logic_vector(31 downto 0) := (others => '0');
--signal cond_lsl, cond_lsr, cond_asr, cond_ror, cond_rrx : boolean;
--signal one : std_logic_vector(31 downto 0) := X"FFFFFFFF";
signal cout_lsl, cout_alrsr : std_logic;
signal shift_i : integer;
begin

--   zero <= (others =>  '0');
--   one  <= (others =>  '1');

  shift_i <= to_integer(unsigned(shift_val));
  
--   cond_lsl <= (shift_lsl and not(shift_lsr) and not(shift_asr) and not(shift_ror) and not(shift_rrx)) = '1';
--   cond_lsr <= (shift_lsr and not(shift_lsl) and not(shift_asr) and not(shift_ror) and not(shift_rrx)) = '1';
--   cond_asr <= (shift_asr and not(shift_lsl) and not(shift_lsr) and not(shift_ror) and not(shift_rrx)) = '1';
--   cond_ror <= (shift_ror and not(shift_lsl) and not(shift_lsr) and not(shift_asr) and not(shift_rrx)) = '1';
--   cond_rrx <= ((shift_rrx and not(shift_lsl) and not(shift_lsr) and not(shift_asr) and not(shift_ror)) = '1' and shift_val = "00000");

--   msb_asr <= zero when din(31) = '0' else one;

  dout <= std_logic_vector(shift_left  (unsigned(din), shift_i)) when shift_lsl = '1' else 
          std_logic_vector(shift_right (unsigned(din), shift_i)) when shift_lsr = '1' else
          std_logic_vector(shift_right (  signed(din), shift_i)) when shift_asr = '1' else
          std_logic_vector(rotate_right(unsigned(din), shift_i)) when shift_ror = '1' else
          cin & din(31 downto 1)                                 when shift_rrx = '1' else
          din;

  cout_lsl <= din(32-shift_i) when shift_i > 0 else '0';
  cout_alrsr <= din(shift_i -1) when shift_i > 0 else '0';

  cout <= (cout_lsl)   when shift_lsl = '1' else 
          (cout_alrsr) when shift_lsr = '1' else
          (cout_alrsr) when shift_asr = '1' else
          (cout_alrsr) when shift_ror = '1' else
          din(0)       when shift_rrx = '1' else
          cin;

end behavior;

EXEC/src/ALU.vhdl
LIBRARY IEEE;
use IEEE.std_logic_1164.all;
use IEEE.numeric_std.all;

entity Alu is
    port (  op1 : in  Std_Logic_Vector(31 downto 0);
            op2 : in  Std_Logic_Vector(31 downto 0);
            cin : in  Std_Logic;
            cmd : in  Std_Logic_Vector(1 downto 0);
            res : out Std_Logic_Vector(31 downto 0);
            cout: out Std_Logic;
            z   : out Std_Logic;
            n   : out Std_Logic;
            v   : out Std_Logic;
            vdd : in  bit;
            vss : in  bit);
end Alu;

architecture equ of Alu is
SIGNAL temp : Std_Logic_Vector(32 downto 0);
SIGNAL cin_32 : std_logic_vector(31 downto 0);
SIGNAL cond_v : std_logic;
    BEGIN
    
    cin_32 <= X"0000000" & "000" & cin;
    
    temp <= std_logic_vector(('0'&unsigned(op1)) + ('0'&unsigned(op2)) + ('0'&unsigned(cin_32)));
    
    res <= temp(31 downto 0) when cmd="00"
           else op1 and op2  when cmd="01"
           else op1 or  op2  when cmd="10"
           else op1 xor op2  when cmd="11";

    cout <= temp(32);
    z <= '1' when temp(31 downto 0) = x"00000000" else '0';
    n <= '1' when temp(31) = '1' else '0';
    cond_v <= ( ((not(op1(31))) and (not(op2(31))) and (temp(31))) or (op1(31) and op2(31) and (not(temp(31)))) );
    v <= '1' when cond_v = '1' else '0';
    
end equ;

PROCESSEUR_VF/EXEC/exec.vhdl
library ieee;
use ieee.std_logic_1164.all;
use ieee.numeric_std.all;

entity EXEC is
	port(
	-- Decode interface synchro
			dec2exe_empty	: in Std_logic;
			exe_pop			: out Std_logic;

	-- Decode interface operands
			dec_op1			: in Std_Logic_Vector(31 downto 0); -- first alu input
			dec_op2			: in Std_Logic_Vector(31 downto 0); -- shifter input
			dec_exe_dest	: in Std_Logic_Vector(3 downto 0); -- Rd destination     Pour le !
			dec_exe_wb		: in Std_Logic; -- Rd destination write back             Equivalent au ! (??????)
			dec_flag_wb		: in Std_Logic; -- CSPR modifiy                          Equivalent au S (??????)

	-- Decode to mem interface 
			dec_mem_data	: in Std_Logic_Vector(31 downto 0); -- data to MEM W     
			dec_mem_dest	: in Std_Logic_Vector(3 downto 0); -- Destination MEM R
			dec_pre_index 	: in Std_logic;                                        --Calcul de l'index (si dec_pre_index = 1) (????????)

			dec_mem_lw		: in Std_Logic;
			dec_mem_lb		: in Std_Logic;
			dec_mem_sw		: in Std_Logic;
			dec_mem_sb		: in Std_Logic;

	-- Shifter command
			dec_shift_lsl	: in Std_Logic;
			dec_shift_lsr	: in Std_Logic; 
			dec_shift_asr	: in Std_Logic;
			dec_shift_ror	: in Std_Logic;
			dec_shift_rrx	: in Std_Logic;
			dec_shift_val	: in Std_Logic_Vector(4 downto 0);
			dec_cy				: in Std_Logic;

	-- Alu operand selection
			dec_comp_op1	: in Std_Logic;
			dec_comp_op2	: in Std_Logic;
			dec_alu_cy 		: in Std_Logic;

	-- Alu command
			dec_alu_cmd		: in Std_Logic_Vector(1 downto 0);

	-- Exe bypass to decod
			exe_res			: out Std_Logic_Vector(31 downto 0);

			exe_c			: out Std_Logic;
			exe_v			: out Std_Logic;
			exe_n			: out Std_Logic;
			exe_z			: out Std_Logic;

			exe_dest		: out Std_Logic_Vector(3 downto 0); -- Rd destination
			exe_wb			: out Std_Logic; -- Rd destination write back
			exe_flag_wb		: out Std_Logic; -- CSPR modifiy

	-- Mem interface
			exe_mem_adr		: out Std_Logic_Vector(31 downto 0); -- Alu res register
			exe_mem_data	: out Std_Logic_Vector(31 downto 0);
			exe_mem_dest	: out Std_Logic_Vector(3 downto 0);

			exe_mem_lw		: out Std_Logic;
			exe_mem_lb		: out Std_Logic;
			exe_mem_sw		: out Std_Logic;
			exe_mem_sb		: out Std_Logic;

			exe2mem_empty	: out Std_logic;
			mem_pop			: in Std_logic;

	-- global interface
			ck				: in Std_logic;
			reset_n			: in Std_logic;
			vdd				: in bit;
			vss				: in bit);
end EXEC;

----------------------------------------------------------------------

architecture struct of EXEC is
--signaux interne pour l'ALU
signal mux_op1,mux_op2,res_alu : std_logic_vector(31 downto 0);
signal cout_alu, cout_alu_wb : std_logic;
--signaux interne pour le SHIFTER
signal dout_shift : std_logic_vector(31 downto 0);
signal cout_shift : std_logic;
--signaux interne pour l'indexation
signal mem_adr : std_logic_vector(31 downto 0); --sortie du mux entre alu et dec_op1
--singaux de gestion de la fifo ??????
signal exe_push, exe2mem_full : std_logic;

begin
--  Component instantiation.

	ALU : entity work.ALU(equ) 
	PORT MAP(op1 => mux_op1    ,
					 op2 => mux_op2    , 
					 cin => dec_alu_cy ,
					 cmd => dec_alu_cmd,
					 res => res_alu    ,
					 cout=> cout_alu   ,
					 z   => exe_z      ,
					 n   => exe_n      , 
					 v   => exe_v      , 
					 vdd => vdd        ,
					 vss => vss        );

	SHIFTER : entity work.shifter(behavior) 
	PORT MAP(shift_lsl => dec_shift_lsl,
			 shift_lsr => dec_shift_lsr,
			 shift_asr => dec_shift_asr,
			 shift_ror => dec_shift_ror,
			 shift_rrx => dec_shift_rrx,
			 shift_val => dec_shift_val,
			 din       => dec_op2      ,
			 cin       => dec_cy       ,
			 dout      => dout_shift   ,
			 cout      => cout_shift   ,
			 vdd       => vdd          ,
			 vss       => vss          );

	exec2mem : entity work.fifo_72b(dataflow)
	port map (	din(71)	 => dec_mem_lw,
				din(70)	 => dec_mem_lb,
				din(69)	 => dec_mem_sw,
				din(68)	 => dec_mem_sb,

				din(67 downto 64) => dec_mem_dest,
				din(63 downto 32) => dec_mem_data,
				din(31 downto 0)  => mem_adr,

				dout(71) => exe_mem_lw,
				dout(70) => exe_mem_lb,
				dout(69) => exe_mem_sw,
				dout(68) => exe_mem_sb,

				dout(67 downto 64) => exe_mem_dest,
				dout(63 downto 32) => exe_mem_data,
				dout(31 downto 0)  => exe_mem_adr,

				push => exe_push,
				pop	 => mem_pop,

				empty => exe2mem_empty,
				full  => exe2mem_full,

				reset_n	=> reset_n,
				ck		=> ck,
				vdd		=> vdd,
				vss		=> vss);

--Implementation des multiplexeurs de choix des opérandes 
	mux_op1 <= dec_op1    when dec_comp_op1 = '0' else not(dec_op1);
	mux_op2 <= dout_shift when dec_comp_op2 = '0' else not(dout_shift);

--Gestion du Writeback de res_alu
	exe_wb   <= dec_exe_wb  ;
	exe_res  <= res_alu     ; --Attention quand exe_res = X"00000000";
	exe_dest <= dec_exe_dest; --Attention quand exe_dest : R0;

--Gestion du Writeback des flags C, V, Z, N
    --LE signal dec_flag_wb 
	exe_flag_wb <= dec_flag_wb;
	--Implementation du multiplexeur du choix des cout (ALU ou shifter)
	exe_c <= '0'      when reset_n = '0'      else 
	         cout_alu when dec_alu_cmd = "00" else
			 cout_shift;

--Implementation du multiplexeur de pre/post indexation
	mem_adr <= res_alu when dec_pre_index = '1' else dec_op1;

--Gestion interface synchro
	exe_pop	<= '1' when ((not(dec2exe_empty) and not(exe2mem_full)) = '1') else '0'; 

--Gestion de la fifo
	exe_push <= '1' when exe2mem_full = '0' and (dec_mem_sb or dec_mem_sw or dec_mem_lb or dec_mem_lw) ='1' else '0'; --ajout de condition

end struct;

EXEC/testbench/test_tb.vhdl
library ieee;
use ieee.std_logic_1164.all;
use ieee.numeric_std.all;

entity test_tb is
end test_tb;

architecture struct of test_tb is
    constant clk_period : time := 2 ns;
    -- Decode interface synchro
    signal dec2exe_empty, exe_pop : std_logic;
    -- Decode interface operands
    signal dec_op1, dec_op2        : std_logic_vector(31 downto 0);
    signal dec_exe_dest            : std_logic_vector(3 downto 0);
    signal dec_exe_wb, dec_flag_wb : std_logic;
    -- Decode to mem interface
    signal dec_mem_data : std_logic_vector(31 downto 0);
    signal dec_mem_dest : std_logic_vector(3 downto 0);
    signal dec_pre_index: std_logic;
    signal dec_mem_lw, dec_mem_lb, dec_mem_sw, dec_mem_sb : std_logic;
    -- Shifter command
    signal dec_shift_lsl, dec_shift_lsr, dec_shift_asr, dec_shift_ror, dec_shift_rrx, dec_cy : std_logic;
    signal dec_shift_val : std_logic_vector(4 downto 0);
    --Alu operand selection
    signal dec_comp_op1, dec_comp_op2, dec_alu_cy : std_logic;
    --Alu command
    signal dec_alu_cmd : std_logic_vector(1 downto 0);
    --Exe bypass to decod
    signal exe_res : std_logic_vector(31 downto 0);
    signal exe_c, exe_v, exe_n, exe_z : std_logic;
    signal exe_dest : std_logic_vector(3 downto 0);
    signal exe_wb, exe_flag_wb : std_logic;
    --Mem Interface
    signal exe_mem_adr, exe_mem_data : std_logic_vector(31 downto 0);
    signal exe_mem_dest : std_logic_vector(3 downto 0);
    signal exe_mem_lw, exe_mem_lb, exe_mem_sw, exe_mem_sb, exe2mem_empty, mem_pop : std_logic;
    --global interface
    signal ck, reset_n : std_logic;
    signal vdd, vss : bit;
begin

    EXEC : entity work.exec(struct) PORT MAP(-- Decode interface synchro
                                                dec2exe_empty	=> dec2exe_empty,
			                                    exe_pop			=> exe_pop,

                                            -- Decode interface operands
                                                dec_op1			=> dec_op1     , -- first alu input
                                                dec_op2			=> dec_op2     , -- shifter input
                                                dec_exe_dest	=> dec_exe_dest, -- Rd destination     Pour le !
                                                dec_exe_wb		=> dec_exe_wb  , -- Rd destination write back             Equivalent au ! (??????)
                                                dec_flag_wb		=> dec_flag_wb , -- CSPR modifiy                          Equivalent au S (??????)

                                            -- Decode to mem interface 
                                                dec_mem_data	=> dec_mem_data , -- data to MEM W     
                                                dec_mem_dest	=> dec_mem_dest , -- Destination MEM R
                                                dec_pre_index 	=> dec_pre_index,                                        --Calcul de l'index (si dec_pre_index = 1) (????????)

                                                dec_mem_lw		=> dec_mem_lw,
                                                dec_mem_lb		=> dec_mem_lb,
                                                dec_mem_sw		=> dec_mem_sw,
                                                dec_mem_sb		=> dec_mem_sb,

                                            -- Shifter command
                                                dec_shift_lsl	=> dec_shift_lsl,
                                                dec_shift_lsr	=> dec_shift_lsr, 
                                                dec_shift_asr	=> dec_shift_asr,
                                                dec_shift_ror	=> dec_shift_ror,
                                                dec_shift_rrx	=> dec_shift_rrx,
                                                dec_shift_val	=> dec_shift_val,
                                                dec_cy			=> dec_cy       ,

                                            -- Alu operand selection
                                                dec_comp_op1	=> dec_comp_op1,
                                                dec_comp_op2	=> dec_comp_op2,
                                                dec_alu_cy 		=> dec_alu_cy  ,

                                            -- Alu command
                                                dec_alu_cmd		=> dec_alu_cmd,

                                            -- Exe bypass to decod
                                                exe_res			=> exe_res,
 
                                                exe_c			=> exe_c,
                                                exe_v			=> exe_v,
                                                exe_n			=> exe_n,
                                                exe_z			=> exe_z,
 
                                                exe_dest		=> exe_dest   , -- Rd destination
                                                exe_wb			=> exe_wb     , -- Rd destination write back
                                                exe_flag_wb		=> exe_flag_wb, -- CSPR modifiy

                                            -- Mem interface
                                                exe_mem_adr		=> exe_mem_adr , -- Alu res register
                                                exe_mem_data	=> exe_mem_data,
                                                exe_mem_dest	=> exe_mem_dest,

                                                exe_mem_lw		=> exe_mem_lw,
                                                exe_mem_lb		=> exe_mem_lb,
                                                exe_mem_sw		=> exe_mem_sw,
                                                exe_mem_sb		=> exe_mem_sb,

                                                exe2mem_empty	=> exe2mem_empty,
                                                mem_pop			=> mem_pop      ,

                                            -- global interface
                                                ck				=> ck     ,
                                                reset_n			=> reset_n,
                                                vdd				=> vdd    ,
                                                vss				=> vss);
    -- Decode interface synchro
    dec2exe_empty <= '1', '0' after 5  ns, '1' after 7  ns,
                          '0' after 9  ns, '1' after 11 ns,
                          '0' after 21 ns, '1' after 23 ns;

    --gestion fifo mem interface
    mem_pop <= '0', '1' after 6  ns, '0' after 8  ns,
                    '1' after 8.5 ns, '0' after 11 ns,
                    '1' after 18 ns, '0' after 20 ns;

    -- Decode interface operands
    dec_op1      <= X"00000000", X"F0F0F0F0" after 5 ns, X"ABCD1234" after 9 ns, X"00000000" after 21 ns;
    dec_op2      <= X"00000000", X"00001111" after 5 ns, X"00000100" after 9 ns, X"00000005" after 21 ns;   
    dec_exe_dest <= X"0", X"5" after 5 ns, X"A" after 9 ns, X"6" after 21 ns;
    dec_exe_wb   <= '0', '1' after 5 ns;
    dec_flag_wb  <= '0', '1' after 5 ns;

    -- Decode to mem interface
    dec_mem_data <= X"01000000", X"0000ABCD" after 21 ns;
    dec_mem_dest <= "0000", X"B" after 21 ns;
    dec_pre_index<= '1';

    dec_mem_lw   <= '0', '1' after 6 ns, '0' after 8 ns;
    dec_mem_lb   <= '0';
    dec_mem_sw   <= '0', '1' after 10 ns, '0' after 12 ns, '1' after 22 ns, '0' after 24 ns;
    dec_mem_sb   <= '0';

    -- Shifter command
    dec_shift_lsl <= '0', '1' after 5 ns, '0' after 7 ns;
    dec_shift_lsr <= '0';
    dec_shift_asr <= '0', '1' after 9 ns, '0' after 11 ns;
    dec_shift_ror <= '0';
    dec_shift_rrx <= '0';
    dec_shift_val <= "00000", "00101" after 5 ns, "00011" after 9 ns, "00000" after 11 ns;
    dec_cy        <= '0';

    -- Alu operand selection
    dec_comp_op1 <= '0';
    dec_comp_op2 <= '0', '0' after 21 ns;
    dec_alu_cy   <= '0', '1' after 21 ns;

    -- Alu command
    dec_alu_cmd <= "00", "01" after 9 ns, "00" after 21 ns;

    reset_n <= '0' , '1' after 2 ns;

    clk_gen:process
    begin
        ck <= '0';
        wait for clk_period/2;
        ck <= '1';
        wait for clk_period/2;
    end process;

end struct;

EXEC/work/test_tb.vcd
$date
  Sun Dec 31 00:39:24 2023
$end
$version
  GHDL v0
$end
$timescale
  1 fs
$end
$scope module standard $end
$upscope $end
$scope module std_logic_1164 $end
$upscope $end
$scope module numeric_std $end
$upscope $end
$scope module test_tb $end
$var reg 1 ! dec2exe_empty $end
$var reg 1 " exe_pop $end
$var reg 32 # dec_op1[31:0] $end
$var reg 32 $ dec_op2[31:0] $end
$var reg 4 % dec_exe_dest[3:0] $end
$var reg 1 & dec_exe_wb $end
$var reg 1 ' dec_flag_wb $end
$var reg 32 ( dec_mem_data[31:0] $end
$var reg 4 ) dec_mem_dest[3:0] $end
$var reg 1 * dec_pre_index $end
$var reg 1 + dec_mem_lw $end
$var reg 1 , dec_mem_lb $end
$var reg 1 - dec_mem_sw $end
$var reg 1 . dec_mem_sb $end
$var reg 1 / dec_shift_lsl $end
$var reg 1 0 dec_shift_lsr $end
$var reg 1 1 dec_shift_asr $end
$var reg 1 2 dec_shift_ror $end
$var reg 1 3 dec_shift_rrx $end
$var reg 1 4 dec_cy $end
$var reg 5 5 dec_shift_val[4:0] $end
$var reg 1 6 dec_comp_op1 $end
$var reg 1 7 dec_comp_op2 $end
$var reg 1 8 dec_alu_cy $end
$var reg 2 9 dec_alu_cmd[1:0] $end
$var reg 32 : exe_res[31:0] $end
$var reg 1 ; exe_c $end
$var reg 1 < exe_v $end
$var reg 1 = exe_n $end
$var reg 1 > exe_z $end
$var reg 4 ? exe_dest[3:0] $end
$var reg 1 @ exe_wb $end
$var reg 1 A exe_flag_wb $end
$var reg 32 B exe_mem_adr[31:0] $end
$var reg 32 C exe_mem_data[31:0] $end
$var reg 4 D exe_mem_dest[3:0] $end
$var reg 1 E exe_mem_lw $end
$var reg 1 F exe_mem_lb $end
$var reg 1 G exe_mem_sw $end
$var reg 1 H exe_mem_sb $end
$var reg 1 I exe2mem_empty $end
$var reg 1 J mem_pop $end
$var reg 1 K ck $end
$var reg 1 L reset_n $end
$var reg 1 M vdd $end
$var reg 1 N vss $end
$scope module exec $end
$var reg 1 O dec2exe_empty $end
$var reg 1 P exe_pop $end
$var reg 32 Q dec_op1[31:0] $end
$var reg 32 R dec_op2[31:0] $end
$var reg 4 S dec_exe_dest[3:0] $end
$var reg 1 T dec_exe_wb $end
$var reg 1 U dec_flag_wb $end
$var reg 32 V dec_mem_data[31:0] $end
$var reg 4 W dec_mem_dest[3:0] $end
$var reg 1 X dec_pre_index $end
$var reg 1 Y dec_mem_lw $end
$var reg 1 Z dec_mem_lb $end
$var reg 1 [ dec_mem_sw $end
$var reg 1 \ dec_mem_sb $end
$var reg 1 ] dec_shift_lsl $end
$var reg 1 ^ dec_shift_lsr $end
$var reg 1 _ dec_shift_asr $end
$var reg 1 ` dec_shift_ror $end
$var reg 1 a dec_shift_rrx $end
$var reg 5 b dec_shift_val[4:0] $end
$var reg 1 c dec_cy $end
$var reg 1 d dec_comp_op1 $end
$var reg 1 e dec_comp_op2 $end
$var reg 1 f dec_alu_cy $end
$var reg 2 g dec_alu_cmd[1:0] $end
$var reg 32 h exe_res[31:0] $end
$var reg 1 i exe_c $end
$var reg 1 j exe_v $end
$var reg 1 k exe_n $end
$var reg 1 l exe_z $end
$var reg 4 m exe_dest[3:0] $end
$var reg 1 n exe_wb $end
$var reg 1 o exe_flag_wb $end
$var reg 32 p exe_mem_adr[31:0] $end
$var reg 32 q exe_mem_data[31:0] $end
$var reg 4 r exe_mem_dest[3:0] $end
$var reg 1 s exe_mem_lw $end
$var reg 1 t exe_mem_lb $end
$var reg 1 u exe_mem_sw $end
$var reg 1 v exe_mem_sb $end
$var reg 1 w exe2mem_empty $end
$var reg 1 x mem_pop $end
$var reg 1 y ck $end
$var reg 1 z reset_n $end
$var reg 1 { vdd $end
$var reg 1 | vss $end
$var reg 32 } mux_op1[31:0] $end
$var reg 32 !" mux_op2[31:0] $end
$var reg 32 "" res_alu[31:0] $end
$var reg 1 #" cout_alu $end
$var reg 1 $" cout_alu_wb $end
$var reg 32 %" dout_shift[31:0] $end
$var reg 1 &" cout_shift $end
$var reg 32 '" mem_adr[31:0] $end
$var reg 1 (" exe_push $end
$var reg 1 )" exe2mem_full $end
$scope module alu $end
$var reg 32 *" op1[31:0] $end
$var reg 32 +" op2[31:0] $end
$var reg 1 ," cin $end
$var reg 2 -" cmd[1:0] $end
$var reg 32 ." res[31:0] $end
$var reg 1 /" cout $end
$var reg 1 0" z $end
$var reg 1 1" n $end
$var reg 1 2" v $end
$var reg 1 3" vdd $end
$var reg 1 4" vss $end
$var reg 33 5" temp[32:0] $end
$var reg 32 6" cin_32[31:0] $end
$var reg 1 7" cond_v $end
$upscope $end
$scope module shifter $end
$var reg 1 8" shift_lsl $end
$var reg 1 9" shift_lsr $end
$var reg 1 :" shift_asr $end
$var reg 1 ;" shift_ror $end
$var reg 1 <" shift_rrx $end
$var reg 5 =" shift_val[4:0] $end
$var reg 32 >" din[31:0] $end
$var reg 1 ?" cin $end
$var reg 32 @" dout[31:0] $end
$var reg 1 A" cout $end
$var reg 1 B" vdd $end
$var reg 1 C" vss $end
$var reg 1 D" cout_lsl $end
$var reg 1 E" cout_alrsr $end
$var integer 32 F" shift_i $end
$upscope $end
$scope module exec2mem $end
$var reg 72 G" din[71:0] $end
$var reg 72 H" dout[71:0] $end
$var reg 1 I" push $end
$var reg 1 J" pop $end
$var reg 1 K" full $end
$var reg 1 L" empty $end
$var reg 1 M" reset_n $end
$var reg 1 N" ck $end
$var reg 1 O" vdd $end
$var reg 1 P" vss $end
$var reg 72 Q" fifo_d[71:0] $end
$var reg 1 R" fifo_v $end
$upscope $end
$upscope $end
$upscope $end
$enddefinitions $end
#0
1!
0"
b00000000000000000000000000000000 #
b00000000000000000000000000000000 $
b0000 %
0&
0'
b00000001000000000000000000000000 (
b0000 )
1*
0+
0,
0-
0.
0/
00
01
02
03
04
b00000 5
06
07
08
b00 9
b00000000000000000000000000000000 :
0;
0<
0=
1>
b0000 ?
0@
0A
bUUUUUUUUUUUUUUUUUUUUUUUUUUUUUUUU B
bUUUUUUUUUUUUUUUUUUUUUUUUUUUUUUUU C
bUUUU D
UE
UF
UG
UH
UI
0J
0K
0L
0M
0N
1O
0P
b00000000000000000000000000000000 Q
b00000000000000000000000000000000 R
b0000 S
0T
0U
b00000001000000000000000000000000 V
b0000 W
1X
0Y
0Z
0[
0\
0]
0^
0_
0`
0a
b00000 b
0c
0d
0e
0f
b00 g
b00000000000000000000000000000000 h
0i
0j
0k
1l
b0000 m
0n
0o
bUUUUUUUUUUUUUUUUUUUUUUUUUUUUUUUU p
bUUUUUUUUUUUUUUUUUUUUUUUUUUUUUUUU q
bUUUU r
Us
Ut
Uu
Uv
Uw
0x
0y
0z
0{
0|
b00000000000000000000000000000000 }
b00000000000000000000000000000000 !"
b00000000000000000000000000000000 ""
0#"
U$"
b00000000000000000000000000000000 %"
0&"
b00000000000000000000000000000000 '"
0("
0)"
b00000000000000000000000000000000 *"
b00000000000000000000000000000000 +"
0,"
b00 -"
b00000000000000000000000000000000 ."
0/"
10"
01"
02"
03"
04"
b000000000000000000000000000000000 5"
b00000000000000000000000000000000 6"
07"
08"
09"
0:"
0;"
0<"
b00000 ="
b00000000000000000000000000000000 >"
0?"
b00000000000000000000000000000000 @"
0A"
0B"
0C"
0D"
0E"
b0 F"
b000000000000000100000000000000000000000000000000000000000000000000000000 G"
bUUUUUUUUUUUUUUUUUUUUUUUUUUUUUUUUUUUUUUUUUUUUUUUUUUUUUUUUUUUUUUUUUUUUUUUU H"
0I"
0J"
0K"
UL"
0M"
0N"
0O"
0P"
bUUUUUUUUUUUUUUUUUUUUUUUUUUUUUUUUUUUUUUUUUUUUUUUUUUUUUUUUUUUUUUUUUUUUUUUU Q"
UR"
#1000000
1I
1K
1w
1y
1L"
1N"
0R"
#2000000
0K
1L
0y
1z
1M"
0N"
#3000000
1K
1y
1N"
#4000000
0K
0y
0N"
#5000000
0!
1"
b11110000111100001111000011110000 #
b00000000000000000001000100010001 $
b0101 %
1&
1'
1/
b00101 5
b11110000111100110001001100010000 :
1=
0>
b0101 ?
1@
1A
1K
0O
1P
b11110000111100001111000011110000 Q
b00000000000000000001000100010001 R
b0101 S
1T
1U
1]
b00101 b
b11110000111100110001001100010000 h
1k
0l
b0101 m
1n
1o
1y
b11110000111100001111000011110000 }
b00000000000000100010001000100000 !"
b11110000111100110001001100010000 ""
b00000000000000100010001000100000 %"
b11110000111100110001001100010000 '"
b11110000111100001111000011110000 *"
b00000000000000100010001000100000 +"
b11110000111100110001001100010000 ."
00"
11"
b011110000111100110001001100010000 5"
18"
b00101 ="
b00000000000000000001000100010001 >"
b00000000000000100010001000100000 @"
1E"
b101 F"
b000000000000000100000000000000000000000011110000111100110001001100010000 G"
1N"
#6000000
1+
1J
0K
1Y
1x
0y
1("
b100000000000000100000000000000000000000011110000111100110001001100010000 G"
1I"
1J"
0N"
#7000000
1!
0"
0/
b11110000111100010000001000000001 :
b11110000111100110001001100010000 B
b00000001000000000000000000000000 C
b0000 D
1E
0F
0G
0H
0I
1K
1O
0P
0]
b11110000111100010000001000000001 h
b11110000111100110001001100010000 p
b00000001000000000000000000000000 q
b0000 r
1s
0t
0u
0v
0w
1y
b00000000000000000001000100010001 !"
b11110000111100010000001000000001 ""
b00000000000000000001000100010001 %"
b11110000111100010000001000000001 '"
b00000000000000000001000100010001 +"
b11110000111100010000001000000001 ."
b011110000111100010000001000000001 5"
08"
b00000000000000000001000100010001 @"
b100000000000000100000000000000000000000011110000111100010000001000000001 G"
b100000000000000100000000000000000000000011110000111100110001001100010000 H"
0L"
1N"
b100000000000000100000000000000000000000011110000111100110001001100010000 Q"
1R"
#8000000
0+
0J
0K
0Y
0x
0y
0("
1)"
b000000000000000100000000000000000000000011110000111100010000001000000001 G"
0I"
0J"
1K"
0N"
#8500000
1J
1x
0)"
1J"
0K"
#9000000
0!
1"
b10101011110011010001001000110100 #
b00000000000000000000000100000000 $
b1010 %
11
b00011 5
b01 9
b00000000000000000000000000100000 :
0;
b1010 ?
1I
1K
0O
1P
b10101011110011010001001000110100 Q
b00000000000000000000000100000000 R
b1010 S
1_
b00011 b
b01 g
b00000000000000000000000000100000 h
0i
b1010 m
1w
1y
b10101011110011010001001000110100 }
b00000000000000000000000000100000 !"
b00000000000000000000000000100000 ""
b00000000000000000000000000100000 %"
0&"
b00000000000000000000000000100000 '"
b10101011110011010001001000110100 *"
b00000000000000000000000000100000 +"
b01 -"
b00000000000000000000000000100000 ."
b010101011110011010001001001010100 5"
1:"
b00011 ="
b00000000000000000000000100000000 >"
b00000000000000000000000000100000 @"
0A"
0E"
b11 F"
b000000000000000100000000000000000000000000000000000000000000000000100000 G"
1L"
1N"
0R"
#10000000
1-
0K
1[
0y
1("
b001000000000000100000000000000000000000000000000000000000000000000100000 G"
1I"
0N"
#11000000
1!
0"
01
b00000 5
b00000000000000000000000000000000 :
b00000000000000000000000000100000 B
0E
1G
0I
0J
1K
1O
0P
0_
b00000 b
b00000000000000000000000000000000 h
b00000000000000000000000000100000 p
0s
1u
0w
0x
1y
b00000000000000000000000100000000 !"
b00000000000000000000000000000000 ""
b00000000000000000000000100000000 %"
b00000000000000000000000000000000 '"
0("
1)"
b00000000000000000000000100000000 +"
b00000000000000000000000000000000 ."
b010101011110011010001001100110100 5"
0:"
b00000 ="
b00000000000000000000000100000000 @"
b0 F"
b001000000000000100000000000000000000000000000000000000000000000000000000 G"
b001000000000000100000000000000000000000000000000000000000000000000100000 H"
0I"
0J"
1K"
0L"
1N"
b001000000000000100000000000000000000000000000000000000000000000000100000 Q"
1R"
#12000000
0-
0K
0[
0y
b000000000000000100000000000000000000000000000000000000000000000000000000 G"
0N"
#13000000
1K
1y
1N"
#14000000
0K
0y
0N"
#15000000
1K
1y
1N"
#16000000
0K
0y
0N"
#17000000
1K
1y
1N"
#18000000
1J
0K
1x
0y
0)"
1J"
0K"
0N"
#19000000
1I
1K
1w
1y
1L"
1N"
0R"
#20000000
0J
0K
0x
0y
0J"
0N"
