DEC/src/REG.vhdl
library ieee;
use ieee.std_logic_1164.all;
use ieee.numeric_std.all;

entity Reg is
	port(
	-- Write Port 1 prioritaire
		wdata1		    : in Std_Logic_Vector(31 downto 0);
		wadr1			: in Std_Logic_Vector(3 downto 0);
		wen1			: in Std_Logic;

	-- Write Port 2 non prioritaire
		wdata2		    : in Std_Logic_Vector(31 downto 0);
		wadr2			: in Std_Logic_Vector(3 downto 0);
		wen2			: in Std_Logic;

	-- Write CSPR Port
		wcry			: in Std_Logic;
		wzero			: in Std_Logic;
		wneg			: in Std_Logic;
		wovr			: in Std_Logic;
		cspr_wb		    : in Std_Logic;
		
	-- Read Port 1 32 bits
		reg_rd1		    : out Std_Logic_Vector(31 downto 0);
		radr1			: in Std_Logic_Vector(3 downto 0);
		reg_v1		    : out Std_Logic;

	-- Read Port 2 32 bits
		reg_rd2		    : out Std_Logic_Vector(31 downto 0);
		radr2			: in Std_Logic_Vector(3 downto 0);
		reg_v2		    : out Std_Logic;

	-- Read Port 3 32 bits
		reg_rd3		    : out Std_Logic_Vector(31 downto 0);
		radr3			: in Std_Logic_Vector(3 downto 0);
		reg_v3		    : out Std_Logic;

	-- read CSPR Port
		reg_cry		    : out Std_Logic;
		reg_zero		: out Std_Logic;
		reg_neg		    : out Std_Logic;
		reg_cznv		: out Std_Logic;
		reg_ovr		    : out Std_Logic;
		reg_vv		    : out Std_Logic;
		
	-- Invalidate Port 
		inval_adr1	    : in Std_Logic_Vector(3 downto 0);
		inval1		    : in Std_Logic;

		inval_adr2	    : in Std_Logic_Vector(3 downto 0);
		inval2		    : in Std_Logic;

		inval_czn	    : in Std_Logic;
		inval_ovr	    : in Std_Logic;

	-- PC
		reg_pc		    : out Std_Logic_Vector(31 downto 0);
		reg_pcv		    : out Std_Logic;
		inc_pc		    : in Std_Logic;
	
	-- global interface
		ck		        : in Std_Logic;
		reset_n		    : in Std_Logic;
		vdd			    : in bit;
		vss			    : in bit);
end Reg;

architecture Behavior OF Reg is
type Tableau is array(15 downto 0) of std_logic_vector(31 downto 0);
signal R : Tableau;
signal CSPR : std_logic_vector(3 downto 0);
signal CSPR_v : std_logic_vector(1 downto 0);
signal R_v : std_logic_vector(15 downto 0);
begin

    process(ck, reset_n)
    begin
        if reset_n = '0' then
            for i in 0 to 15 loop
                R(i)   <= (others => '0');
                R_v(i) <= '1';
            end loop;
            reg_rd1  <= (others => '0');
            reg_rd2  <= (others => '0');
            reg_rd3  <= (others => '0');
            reg_cry	 <= '0';	  
		    reg_zero <= '0';
		    reg_neg	 <= '0';	  
		    reg_ovr	 <= '0';
            --Registre tous valide au début
            reg_v1   <= '1';
            reg_v2   <= '1';
            reg_v3   <= '1';
            reg_cznv <= '1';
            reg_vv   <= '1';
            CSPR_v   <= "11";
        elsif rising_edge(ck) then
            if(inval1 = '0') then
                for i in 0 to 15 loop
                    if to_integer(unsigned(inval_adr1)) = i then
                        R_v(i) <= '0';
                    end if;
                end loop;
            end if;
            if(inval2 = '0') then
                for i in 0 to 15 loop
                    if to_integer(unsigned(inval_adr2)) = i then
                        R_v(i) <= '0';
                    end if;
                end loop;
            end if;
            if(inval_czn = '0') then
                CSPR_v(1) <= '0';
            end if;
            if(inval_ovr = '0') then
                CSPR_v(0) <= '0';
            end if;
            --écriture dans le banc de registre
            if(wen1 = '1') then       --On regarde si port 1 d'écriture est enable
                for j in 0 to 15 loop
                    if(to_integer(unsigned(wadr1)) = j) then
                        if(R_v(j) = '0') then
                            R(j)   <= wdata1;
                            R_v(j) <= '1';
                        end if;
                    end if;
                end loop;
            end if;
            if(wen2 = '1') then --On regarde si port 2 d'écriture est enable
                for j in 0 to 15 loop
                    if(to_integer(unsigned(wadr2)) = j) then 
                        --On regarde si le port2 écrit sur un registre que port1 est en train d'écrire 
                        if(wen1 = '1' and to_integer(unsigned(wadr1)) /= j) then
                            if(R_v(j) = '0') then
                                R(j)   <= wdata2;
                                R_v(j) <= '1';
                            end if;
                        end if;
                    end if;
                end loop;
            end if;
            --écriture des flags
            if(cspr_wb = '1') then
                if(CSPR_v(1) = '0') then
                    CSPR(3) <= wneg;
                    CSPR(2) <= wzero;
                    CSPR(1) <= wcry;
                    CSPR_v(1) <= '1';
                end if;
                if(CSPR_v(0) = '0') then
                    CSPR(0) <= wovr;
                    CSPR_v(0) <= '1';
                end if;
            end if;

            --Lecture dans le banc de registre
            for i in 0 to 15 loop
                if (to_integer(unsigned(radr1)) = i) then
                    reg_rd1 <= R(i);
                    reg_v1  <= R_v(i);
                end if;
                if (to_integer(unsigned(radr2)) = i) then
                    reg_rd2 <= R(i);
                    reg_v2  <= R_v(i);
                end if;
                if (to_integer(unsigned(radr3)) = i) then
                    reg_rd3 <= R(i);
                    reg_v3  <= R_v(i);
                end if;
            end loop;
            --Lecture des flags

            reg_ovr <= CSPR(0);
            reg_cry <= CSPR(1);
		    reg_zero<= CSPR(2);		
		    reg_neg	<= CSPR(3);	 
            reg_vv  <= CSPR_v(0);    
		    reg_cznv<= CSPR_v(1);
            if (inc_pc ='1')then
                R(15)<= std_logic_vector(unsigned(R(15)) + 4);
            end if;
            reg_pcv<= R_v(15);
            reg_pc <= R(15);
        end if;
    end process;
end Behavior;

DEC/work/REG_tb.vcd
$date
  Wed Nov 15 20:00:03 2023
$end
$version
  GHDL v0
$end
$timescale
  1 fs
$end
$var reg 32 ! wdata1[31:0] $end
$var reg 4 " wadr1[3:0] $end
$var reg 1 # wen1 $end
$var reg 32 $ wdata2[31:0] $end
$var reg 4 % wadr2[3:0] $end
$var reg 1 & wen2 $end
$var reg 1 ' wcry $end
$var reg 1 ( wzero $end
$var reg 1 ) wneg $end
$var reg 1 * wovr $end
$var reg 1 + cspr_wb $end
$var reg 32 , reg_rd1[31:0] $end
$var reg 4 - radr1[3:0] $end
$var reg 1 . reg_v1 $end
$var reg 32 / reg_rd2[31:0] $end
$var reg 4 0 radr2[3:0] $end
$var reg 1 1 reg_v2 $end
$var reg 32 2 reg_rd3[31:0] $end
$var reg 4 3 radr3[3:0] $end
$var reg 1 4 reg_v3 $end
$var reg 1 5 reg_cry $end
$var reg 1 6 reg_zero $end
$var reg 1 7 reg_neg $end
$var reg 1 8 reg_cznv $end
$var reg 1 9 reg_ovr $end
$var reg 1 : reg_vv $end
$var reg 4 ; inval_adr1[3:0] $end
$var reg 1 < inval1 $end
$var reg 4 = inval_adr2[3:0] $end
$var reg 1 > inval2 $end
$var reg 1 ? inval_czn $end
$var reg 1 @ inval_ovr $end
$var reg 32 A reg_pc[31:0] $end
$var reg 1 B reg_pcv $end
$var reg 1 C inc_pc $end
$var reg 1 D ck $end
$var reg 1 E reset_n $end
$var reg 1 F vdd $end
$var reg 1 G vss $end
$scope module reg $end
$var reg 32 H wdata1[31:0] $end
$var reg 4 I wadr1[3:0] $end
$var reg 1 J wen1 $end
$var reg 32 K wdata2[31:0] $end
$var reg 4 L wadr2[3:0] $end
$var reg 1 M wen2 $end
$var reg 1 N wcry $end
$var reg 1 O wzero $end
$var reg 1 P wneg $end
$var reg 1 Q wovr $end
$var reg 1 R cspr_wb $end
$var reg 32 S reg_rd1[31:0] $end
$var reg 4 T radr1[3:0] $end
$var reg 1 U reg_v1 $end
$var reg 32 V reg_rd2[31:0] $end
$var reg 4 W radr2[3:0] $end
$var reg 1 X reg_v2 $end
$var reg 32 Y reg_rd3[31:0] $end
$var reg 4 Z radr3[3:0] $end
$var reg 1 [ reg_v3 $end
$var reg 1 \ reg_cry $end
$var reg 1 ] reg_zero $end
$var reg 1 ^ reg_neg $end
$var reg 1 _ reg_cznv $end
$var reg 1 ` reg_ovr $end
$var reg 1 a reg_vv $end
$var reg 4 b inval_adr1[3:0] $end
$var reg 1 c inval1 $end
$var reg 4 d inval_adr2[3:0] $end
$var reg 1 e inval2 $end
$var reg 1 f inval_czn $end
$var reg 1 g inval_ovr $end
$var reg 32 h reg_pc[31:0] $end
$var reg 1 i reg_pcv $end
$var reg 1 j inc_pc $end
$var reg 1 k ck $end
$var reg 1 l reset_n $end
$var reg 1 m vdd $end
$var reg 1 n vss $end
$comment r is not handled $end
$var reg 4 o cspr[3:0] $end
$var reg 2 p cspr_v[1:0] $end
$var reg 16 q r_v[15:0] $end
$upscope $end
$enddefinitions $end
#0
bUUUUUUUUUUUUUUUUUUUUUUUUUUUUUUUU !
bUUUU "
0#
bUUUUUUUUUUUUUUUUUUUUUUUUUUUUUUUU $
bUUUU %
0&
U'
U(
U)
U*
U+
bUUUUUUUUUUUUUUUUUUUUUUUUUUUUUUUU ,
b0011 -
U.
bUUUUUUUUUUUUUUUUUUUUUUUUUUUUUUUU /
b1010 0
U1
bUUUUUUUUUUUUUUUUUUUUUUUUUUUUUUUU 2
b0011 3
U4
U5
U6
U7
U8
U9
U:
b0011 ;
1<
b0011 =
1>
U?
U@
bUUUUUUUUUUUUUUUUUUUUUUUUUUUUUUUU A
UB
UC
0D
1E
0F
0G
bUUUUUUUUUUUUUUUUUUUUUUUUUUUUUUUU H
bUUUU I
0J
bUUUUUUUUUUUUUUUUUUUUUUUUUUUUUUUU K
bUUUU L
0M
UN
UO
UP
UQ
UR
bUUUUUUUUUUUUUUUUUUUUUUUUUUUUUUUU S
b0011 T
UU
bUUUUUUUUUUUUUUUUUUUUUUUUUUUUUUUU V
b1010 W
UX
bUUUUUUUUUUUUUUUUUUUUUUUUUUUUUUUU Y
b0011 Z
U[
U\
U]
U^
U_
U`
Ua
b0011 b
1c
b0011 d
1e
Uf
Ug
bUUUUUUUUUUUUUUUUUUUUUUUUUUUUUUUU h
Ui
Uj
0k
1l
0m
0n
bUUUU o
bUU p
bUUUUUUUUUUUUUUUU q
#500000
1D
1k
#1000000
b00000000000000000000000000000000 ,
1.
b00000000000000000000000000000000 /
11
b00000000000000000000000000000000 2
14
05
06
07
18
09
1:
0D
0E
b00000000000000000000000000000000 S
1U
b00000000000000000000000000000000 V
1X
b00000000000000000000000000000000 Y
1[
0\
0]
0^
1_
0`
1a
0k
0l
b11 p
b1111111111111111 q
#1500000
1D
1k
#2000000
0<
0D
1E
0c
0k
1l
#2500000
U5
U6
U7
U9
b00000000000000000000000000000000 A
1B
1D
U\
U]
U^
U`
b00000000000000000000000000000000 h
1i
1k
b1111111111110111 q
#3000000
1<
0>
0D
1c
0e
0k
#3500000
0.
04
1D
0U
0[
1k
#4000000
1>
0D
1e
0k
#4500000
1D
1k
#5000000
b00010010001101001010101111001101 !
b0011 "
1#
b00001010101100010010011001000111 $
b0011 %
1&
0D
b00010010001101001010101111001101 H
b0011 I
1J
b00001010101100010010011001000111 K
b0011 L
1M
0k
#5500000
1D
1k
b1111111111111111 q
#6000000
0#
0&
b1010 =
0>
0D
0J
0M
b1010 d
0e
0k
#6500000
b00010010001101001010101111001101 ,
1.
b00010010001101001010101111001101 2
14
1D
b00010010001101001010101111001101 S
1U
b00010010001101001010101111001101 Y
1[
1k
b1111101111111111 q
#7000000
b1010 -
1>
0D
b1010 T
1e
0k
#7500000
b00000000000000000000000000000000 ,
0.
01
1D
b00000000000000000000000000000000 S
0U
0X
1k
#8000000
b00010000000100000001000000010000 $
b1010 %
1&
0D
b00010000000100000001000000010000 K
b1010 L
1M
0k
#8500000
1D
1k
#9000000
0&
0D
0M
0k
#9500000
1D
1k
#10000000
b1010 ;
0<
0D
b1010 b
0c
0k
#10500000
1D
1k
#11000000
1<
0D
1c
0k
#11500000
1D
1k
#12000000
0D
0k
#12500000
1D
1k
#13000000
0D
0k
#13500000
1D
1k
#14000000
0D
0k
#14500000
1D
1k
#15000000
b00010001000100010001000100010001 !
b1010 "
1#
0D
b00010001000100010001000100010001 H
b1010 I
1J
0k
#15500000
1D
1k
b1111111111111111 q
#16000000
0#
0D
0J
0k
#16500000
b00010001000100010001000100010001 ,
1.
b00010001000100010001000100010001 /
11
1D
b00010001000100010001000100010001 S
1U
b00010001000100010001000100010001 V
1X
1k
